Workbook

Sheet Dashboard
C2: Total Collection (Construction) | E2: =Donation!G749 -> 2495038
C3: Expenses | E3: =J13 -> 2391826
C4: Feb | E4: ='Monthly Sheet'!F3 -> 12500
C5: March | E5: ='Monthly Sheet'!K3 -> 8500
C6: April | E6: ='Monthly Sheet'!P3 -> 8500
C7: May | E7: ='Monthly Sheet'!U3 -> 3000
C8: June | E8: ='Monthly Sheet'!Z3 -> 4500
C9: July | E9: ='Monthly Sheet'!AE3 -> 2000
C13: Total In Hand | E13: =Sum(E2,E4,E5,E6,E7,E8, E9,E10,E11)-E3 -> 142212

Sheet Detail1
A1: Voucher Number | B1: Date | C1: Particular | D1: Category | E1: Bill Date | F1: Amount
A2: 1 | B2: 45804 | C2: Contractor Harmeet | D2: Construction | E2: 45958 | F2: 30000
A3: 2 | B3: 45806 | C3: God Idol:Shivling,Nandiji,Jaleri | D3: Idols | E3: 45806 | F3: 31000
A4: 3 | B4: 45806 | C4: Labour food(Harmeet) | D4: Construction | E4: 45958 | F4: 220
A5: 4 | B5: 45807 | C5: Security Guard on sthapana | D5: Event | E5: 45807 | F5: 200
A6: 5 | B6: 45807 | C6: Panditji Dakshina for sthapana | D6: Event | E6: 45807 | F6: 3200
A7: 6 | B7: 45807 | C7: Pooja Ka Saman for sthapana | D7: Event | E7: 45807 | F7: 1000
A8: 7 | B8: 45807 | C8: Labour(Harmeet) for sthapana | D8: Construction | E8: 45958 | F8: 1000
A9: 8 | B9: 45807 | C9: Flower Petal for sthpana | D9: Event | E9: 45807 | F9: 500
A10: 9 | B10: 45807 | C10: Fruit for sthapana & Prasad | D10: Event | E10: 45807 | F10: 1200
A11: 10 | B11: 45807 | C11: God Idol:Nag Devta,Ghanti,Jhanda | D11: Idols | E11: 45807 | F11: 7000
A12: 11 | B12: 45807 | C12: Water Bottles on Sthapana | D12: Event | E12: 45807 | F12: 310
A13: 12 | B13: 45808 | C13: Contractor Harmeet (Payment to Kushal Garg (1000 Bricks) | D13: Construction | E13: 45958 | F13: 7000
... A45: 41 | B45: 45860 | C45: Dholki wala payment by Amit vats | D45: Event | E45: 45860 | F45: 700
A46: 42 | B46: 45860 | C46: Hanuman Ji Photo Payment by Amit Vats | F46: 1000
A47: 43 | B47: 45860 | C47: Steel Drain Jaali, Stone jointer, Chain/Hook & Cast Iron jali payment to Pranay | D47: Construction | E47: 45860 | F47: 450
A48: 44 | B48: 45860 | C48: Elbow(2) & Socket(2) Payment to Jindal Interiors by Gaurav Ji | D48: Construction | E48: 45860 | F48: 560
A49: 45 | B49: 45860 | C49: Tray(1), Container (3), Platic Tubs(2) to Nanda Ji | F49: 3400
A50: 46 | B50: 45861 | C50: Wiper (2) Payment to Nanda Ji | F50: 500
A51: 47 | B51: 45861 | C51: Flex Printing(2) payment to Nanda ji | F51: 240
A52: 48 | B52: 45860 | C52: Payment to mayank for saman(vijay Sharma) | D52: Event | E52: 45860 | F52: 1000
A53: 49 | B53: 45860 | C53: Sundarkand (10), Chunni (2) payment to Mayank | D53: Event | E53: 45860 | F53: 1740
A54: 50 | B54: 45860 | C54: 2 Folding Bed payment to Mayank | D54: Ops | E54: 45858 | F54: 3600
A55: 51 | B55: 45863 | C55: Stool (12) | D55: Ops | E55: 45863 | F55: 5430
A56: 52 | B56: 45857 | C56: 2 Permanent Marker | D56: Ops | E56: 45857 | F56: 70
A57: 53 | B57: 45857 | C57: Tea Advance | D57: Ops | E57: 45857 | F57: 200
A58: 54 | B58: 45864 | C58: Board & Lock (1 each) | D58: Ops | E58: 45864 | F58: 600
A59: 55 | B59: 45865 | C59: Bathroom Fittings - Store | D59: Construction | E59: 45865 | F59: 375
A60: 56 | B60: 45865 | C60: Electrical material for Store(Extension Board) | D60: Ops | E60: 45865 | F60: 300
A61: 57 | B61: 45865 | C61: Electrical material for Store | D61: Ops | E61: 45865 | F61: 1500
A62: 58 | B62: 45865 | C62: Ansh Phool Wala (26/6/2025 to 31/7/2025) payment done | D62: Ops | E62: No Bill | F62: 2720
A63: 59 | B63: 45865 | C63: Musical Instrument for mandir | F63: 550
A64: 60 | B64: 45865 | C64: Glass Fitting (Flat) + Safai Payment | D64: Ops | E64: 45865 | F64: 800
A65: 61 | B65: 45866 | C65: Dariya (5) | D65: Ops | E65: 45878 | F65: 1500
A66: 62 | B66: 45866 | C66: Recipt Books (6) | D66: Ops | E66: 45866 | F66: 700
A67: 63 | B67: 45867 | C67: Tables (2) | D67: Ops | E67: 45867 | F67: 3200
A68: 64 | B68: 45868 | C68: Payment to Harmeet Contractor | D68: Construction | E68: 45958 | F68: 63650
A69: 65 | B69: 45866 | C69: Bedsheet (3) | D69: Ops | E69: 45866 | F69: 800
A70: 66 | B70: 45871 | C70: Washroom Cleaner + Tea,+ Lassi +Notepad | D70: Ops | E70: 45871 | F70: 330
A71: 67 | B71: 45873 | C71: Garbage Bag | D71: Ops | E71: 45873 | F71: 85
A72: 68 | B72: 45869 | C72: Iron Pipes For Shikar | D72: Construction | E72: 45869 | F72: 27027
A73: 69 | B73: 45874 | C73: Payment to Dholki Wala | D73: Event | E73: 45874 | F73: 600
A74: 70 | B74: 45876 | C74: Payment to Harmeet Contractor | D74: Construction | E74: 45958 | F74: 20000
A75: 71 | B75: 45873 | C75: Payment to Kudewala for Jal parwah | D75: Ops | E75: 45873 | F75: 500
A76: 72 | B76: 45879 | C76: 900 Mistri Packets From Meenakshi Chaturvedi + Labour Food | F76: 1840
A77: 73 | B77: 45881 | C77: Mishri Prasad ( 3000 Packets) directly from Neeraj Kashyap | D77: Ops | E77: 45880 | F77: 2600
A78: 74 | B78: 45881 | C78: Steel Jhula for Janamashtami | D78: Event | E78: 45883 | F78: 9300
A79: 75 | B79: 45881 | C79: Payment to Kudewala for Jal parwah | D79: Ops | E79: 45881 | F79: 500
A80: 76 | B80: 45881 | C80: Payment to Shiv Shakti, Manimajra for Mandir Top Kalash (2) | D80: Idols | E80: 45881 | F80: 19500
A81: 77 | B81: 45882 | C81: Payment for Bucket, Mug for Flat | D81: Ops | E81: 45882 | F81: 603
A82: 78 | B82: 45882 | C82: Payment to Harmeet Contractor | D82: Construction | E82: 45958 | F82: 3000
A83: 79 | B83: 45883 | C83: Piegon Net for Windows | D83: Ops | E83: 45883 | F83: 350
A84: 80 | B84: 45885 | C84: Payment to Harmeet Contractor | D84: Construction | E84: 45958 | F84: 5000
A85: 45659 | B85: 45885 | C85: Aradite | D85: Construction | E85: 45884 | F85: 1050
A86: 45690 | B86: 45888 | C86: Payment to Harmeet Contractor | D86: Construction | E86: 45958 | F86: 30000
A87: 45718 | B87: 45885 | C87: Janamashtami - Ballon, Fruits, Disposals, Mandir MCB | D87: Event | E87: 45884 | F87: 4840
A88: 45749 | B88: 45885 | C88: Flower Decoration - Ansh | D88: Ops | E88: No Bill | F88: 4000
A89: 45779 | B89: 45885 | C89: Prashad Container (200) | D89: Event | E89: 45885 | F89: 840
A90: 45810 | B90: 45885 | C90: 56 Bhog Thal | D90: Event | E90: 45885 | F90: 1850
A91: 45840 | B91: 45885 | C91: 10 Crates of Water - Pranay | D91: Event | E91: 45885 | F91: 1000
A92: 45871 | B92: 45885 | C92: 10 Crates of Water - akhilesh | D92: Event | E92: 45885 | F92: 1000
A93: 45902 | B93: 45885 | C93: Lights Decoration (6 Pieces) | D93: Event | E93: 45884 | F93: 4000
A94: 45932 | B94: 45885 | C94: Dhol Wala on janamashtami | D94: Event | E94: 45885 | F94: 1200
A95: 45963 | B95: 45885 | C95: Acrylic colors Big Box for Shivling | D95: Ops | E95: 45885 | F95: 260
A96: 45993 | B96: 45884 | C96: Mathura Peda Prashad for 15th Pooja | D96: Event | E96: 45884 | F96: 1500
A97: 2/13 | B97: 46250 | C97: Cells, Hit & Brush | D97: Ops | E97: 45885 | F97: 725
A98: 2/14 | B98: 45885 | C98: Carry bags (200) For prashad | D98: Event | E98: 45885 | F98: 300
A99: 2/15 | B99: 46253 | C99: Voucher Book(2) | D99: Ops | E99: 45888 | F99: 120
A100: 2/16 | B100: 45889 | C100: Dakshina to Shastri ji (Janamashtami - Thali + Daan Patra : 50%) | D100: Dakshina | E100: 45889 | F100: 7100
A101: 2/17 | B101: 45889 | C101: Naag Devta for Mandir | D101: Idols | E101: 45888 | F101: 5000
A102: 2/18 | B102: 45889 | C102: Chandan & Honey for Mandir | D102: Ops | E102: 45889 | F102: 840
A103: 2/19 | B103: 45892 | C103: Payment for Tent on Janamashtami | D103: Tent | E103: 45885 | F103: 16500
A104: 2/20 | B104: 45892 | C104: Rishi pathar wala payment | D104: Construction | E104: 45892 | F104: 10000
A105: 2/21 | B105: 45894 | C105: Love Catering ( Bhandara Payment - Janamashatami) | D105: Event | E105: 45885 | F105: 33000
A106: 2/22 | B106: 45894 | C106: Chokhat Payment Ti Mani Pal Goyal By Amit Katiyar | D106: Construction | E106: 45890 | F106: 12500
A107: 2/23 | B107: 45895 | C107: Payment for chemical 50 bags, 390 per bag | D107: Construction | E107: 45894 | F107: 19500
A108: 2/23-1 | B108: 45895 | C108: Advance payments for Rack | F108: 1000
A109: 2/24 | B109: 45896 | C109: Rishi pathar wala payment | D109: Construction | E109: 45896 | F109: 20000
A110: 2/25 | B110: 45896 | C110: 20 Cemet Bags - Payment to rishi | D110: Construction | E110: 45896 | F110: 17000
A111: 2/26 | B111: 45899 | C111: Payment to Harmeet Contractor | D111: Construction | E111: 45958 | F111: 30000
A112: 2/27 | B112: 45903 | C112: Payment to Rishi for Plaster Work & Tile Work Tilll2 Sep 2025 | D112: Construction | E112: 45903 | F112: 35000
A113: 2/28 | B113: 45903 | C113: Payment for Dholwala (700) & Jagannath (200) on Chati Event | D113: Ops | E113: 45903 | F113: 900
A114: 2/29 | B114: 45899 | C114: Racks Pending Payment (5650) + Carriage(400) | F114: 6050
A115: 2/30 | B115: 45899 | C115: God Idols: Shiv parivar & Hanuman Ji | D115: Idols | E115: 45899 | F115: 20000
A116: 2/31 | B116: 45906 | C116: Payment to Rishi for the work done on 4th Sep 2025 | D116: Construction | E116: 45906 | F116: 6000
A117: 2/32 | B117: 45907 | C117: Payment to rishi for Work done till 7th Sep 2025 | D117: Construction | E117: 45907 | F117: 12200
A118: 2/33 | B118: 45908 | C118: Payment for Red Stone & Carriage in cash | D118: Construction | E118: 45917 | F118: 6300
A119: 2/34 | B119: 45907 | C119: Red Stone Online Payment by mayank | D119: Construction | E119: 45907 | F119: 11340
A120: 2/35 | B120: 45908 | C120: Additional 3 Boxes + Carriage Tiles | D120: Construction | E120: 45904 | F120: 7975
A121: 2/36 | B121: 45908 | C121: Arolite for Mandir | D121: Construction | E121: 45893 | F121: 2000
A122: 2/37 | B122: 45909 | C122: Cement Bags for Outerwalls | D122: Construction | E122: 45909 | F122: 4000
A123: 2/38 | B123: 45909 | C123: Tile Adhesive Outewalls and Top (150 Bags Shiv Durga Mandir NCT - Donation & Expenses | D123: Construction | E123: 45909 | F123: 58500
A124: 2/39 | B124: 45911 | C124: Jeera Bajri 50-50 Ft HARMEET | D124: Construction | E124: 45958 | F124: 3600
A125: 2/40 | B125: 45911 | C125: Rishi pathar wala payment (8 Sep - 11 sep) | D125: Construction | E125: 45911 | F125: 18800
A126: 2/41 | B126: 45913 | C126: Payment to Harmeet Contractor (False Ceiling) | D126: Construction | E126: 45958 | F126: 15000
... A147: 2/62 | B147: 45947 | C147: Red Stone 500ft additional | D147: Construction | E147: 45947 | F147: 15500
A148: 2/63 | B148: 45952 | C148: Payment to Ansh Phool wala | D148: Ops | E148: No Bill | F148: 4800
A149: 2/64 | B149: 45952 | C149: Payment for Mandir work | D149: Ops | E149: 45952 | F149: 7120
A150: 2/65 | B150: 45952 | C150: Mandir Ghee + Honey | F150: 1394
A151: 2/66 | B151: 45952 | C151: Payment for Tent & Water Tanker ( Ankoot) | D151: Event | E151: 45952 | F151: 15500
...

Sheet Expense Statement
A1: Voucher Number | B1: Date | C1: Particular | D1: Category | E1: Bill Date | F1: Amount
A2: 1 | B2: 45804 | C2: Contractor Harmeet | D2: Construction | E2: 45958 | F2: 30000
A3: 2 | B3: 45806 | C3: God Idol:Shivling,Nandiji,Jaleri | D3: Idols | E3: 45806 | F3: 31000
A4: 3 | B4: 45806 | C4: Labour food(Harmeet) | D4: Construction | E4: 45958 | F4: 220
A5: 4 | B5: 45807 | C5: Security Guard on sthapana | D5: Event | E5: 45807 | F5: 200
A6: 5 | B6: 45807 | C6: Panditji Dakshina for sthapana | D6: Event | E6: 45807 | F6: 3200
A7: 6 | B7: 45807 | C7: Pooja Ka Saman for sthapana | D7: Event | E7: 45807 | F7: 1000
A8: 7 | B8: 45807 | C8: Labour(Harmeet) for sthapana | D8: Construction | E8: 45958 | F8: 1000
A9: 8 | B9: 45807 | C9: Flower Petal for sthpana | D9: Event | E9: 45807 | F9: 500
A10: 9 | B10: 45807 | C10: Fruit for sthapana & Prasad | D10: Event | E10: 45807 | F10: 1200
A11: 10 | B11: 45807 | C11: God Idol:Nag Devta,Ghanti,Jhanda | D11: Idols | E11: 45807 | F11: 7000
A12: 11 | B12: 45807 | C12: Water Bottles on Sthapana | D12: Event | E12: 45807 | F12: 310
A13: 12 | B13: 45808 | C13: Contractor Harmeet (Payment to Kushal Garg (1000 Bricks) | D13: Construction | E13: 45958 | F13: 7000
... A45: 41 | B45: 45860 | C45: Dholki wala payment by Amit vats | D45: Event | E45: 45860 | F45: 700
A46: 42 | B46: 45860 | C46: Hanuman Ji Photo Payment by Amit Vats | F46: 1000
A47: 43 | B47: 45860 | C47: Steel Drain Jaali, Stone jointer, Chain/Hook & Cast Iron jali payment to Pranay | D47: Construction | E47: 45860 | F47: 450
A48: 44 | B48: 45860 | C48: Elbow(2) & Socket(2) Payment to Jindal Interiors by Gaurav Ji | D48: Construction | E48: 45860 | F48: 560
A49: 45 | B49: 45860 | C49: Tray(1), Container (3), Platic Tubs(2) to Nanda Ji | F49: 3400
A50: 46 | B50: 45861 | C50: Wiper (2) Payment to Nanda Ji | F50: 500
A51: 47 | B51: 45861 | C51: Flex Printing(2) payment to Nanda ji | F51: 240
A52: 48 | B52: 45860 | C52: Payment to mayank for saman(vijay Sharma) | D52: Event | E52: 45860 | F52: 1000
A53: 49 | B53: 45860 | C53: Sundarkand (10), Chunni (2) payment to Mayank | D53: Event | E53: 45860 | F53: 1740
A54: 50 | B54: 45860 | C54: 2 Folding Bed payment to Mayank | D54: Ops | E54: 45858 | F54: 3600
A55: 51 | B55: 45863 | C55: Stool (12) | D55: Ops | E55: 45863 | F55: 5430
A56: 52 | B56: 45857 | C56: 2 Permanent Marker | D56: Ops | E56: 45857 | F56: 70
A57: 53 | B57: 45857 | C57: Tea Advance | D57: Ops | E57: 45857 | F57: 200
A58: 54 | B58: 45864 | C58: Board & Lock (1 each) | D58: Ops | E58: 45864 | F58: 600
A59: 55 | B59: 45865 | C59: Bathroom Fittings - Store | D59: Construction | E59: 45865 | F59: 375
A60: 56 | B60: 45865 | C60: Electrical material for Store(Extension Board) | D60: Ops | E60: 45865 | F60: 300
A61: 57 | B61: 45865 | C61: Electrical material for Store | D61: Ops | E61: 45865 | F61: 1500
A62: 58 | B62: 45865 | C62: Ansh Phool Wala (26/6/2025 to 31/7/2025) payment done | D62: Ops | E62: No Bill | F62: 2720
A63: 59 | B63: 45865 | C63: Musical Instrument for mandir | F63: 550
A64: 60 | B64: 45865 | C64: Glass Fitting (Flat) + Safai Payment | D64: Ops | E64: 45865 | F64: 800
A65: 61 | B65: 45866 | C65: Dariya (5) | D65: Ops | E65: 45878 | F65: 1500
A66: 62 | B66: 45866 | C66: Recipt Books (6) | D66: Ops | E66: 45866 | F66: 700
A67: 63 | B67: 45867 | C67: Tables (2) | D67: Ops | E67: 45867 | F67: 3200
A68: 64 | B68: 45868 | C68: Payment to Harmeet Contractor | D68: Construction | E68: 45958 | F68: 63650
A69: 65 | B69: 45866 | C69: Bedsheet (3) | D69: Ops | E69: 45866 | F69: 800
A70: 66 | B70: 45871 | C70: Washroom Cleaner + Tea,+ Lassi +Notepad | D70: Ops | E70: 45871 | F70: 330
A71: 67 | B71: 45873 | C71: Garbage Bag | D71: Ops | E71: 45873 | F71: 85
A72: 68 | B72: 45869 | C72: Iron Pipes For Shikar | D72: Construction | E72: 45869 | F72: 27027
A73: 69 | B73: 45874 | C73: Payment to Dholki Wala | D73: Event | E73: 45874 | F73: 600
A74: 70 | B74: 45876 | C74: Payment to Harmeet Contractor | D74: Construction | E74: 45958 | F74: 20000
A75: 71 | B75: 45873 | C75: Payment to Kudewala for Jal parwah | D75: Ops | E75: 45873 | F75: 500
A76: 72 | B76: 45879 | C76: 900 Mistri Packets From Meenakshi Chaturvedi + Labour Food | F76: 1840
A77: 73 | B77: 45881 | C77: Mishri Prasad ( 3000 Packets) directly from Neeraj Kashyap | D77: Ops | E77: 45880 | F77: 2600
A78: 74 | B78: 45881 | C78: Steel Jhula for Janamashtami | D78: Event | E78: 45883 | F78: 9300
A79: 75 | B79: 45881 | C79: Payment to Kudewala for Jal parwah | D79: Ops | E79: 45881 | F79: 500
A80: 76 | B80: 45881 | C80: Payment to Shiv Shakti, Manimajra for Mandir Top Kalash (2) | D80: Idols | E80: 45881 | F80: 19500
A81: 77 | B81: 45882 | C81: Payment for Bucket, Mug for Flat | D81: Ops | E81: 45882 | F81: 603
A82: 78 | B82: 45882 | C82: Payment to Harmeet Contractor | D82: Construction | E82: 45958 | F82: 3000
A83: 79 | B83: 45883 | C83: Piegon Net for Windows | D83: Ops | E83: 45883 | F83: 350
A84: 80 | B84: 45885 | C84: Payment to Harmeet Contractor | D84: Construction | E84: 45958 | F84: 5000
A85: 45659 | B85: 45885 | C85: Aradite | D85: Construction | E85: 45884 | F85: 1050
A86: 45690 | B86: 45888 | C86: Payment to Harmeet Contractor | D86: Construction | E86: 45958 | F86: 30000
A87: 45718 | B87: 45885 | C87: Janamashtami - Ballon, Fruits, Disposals, Mandir MCB | D87: Event | E87: 45884 | F87: 4840
A88: 45749 | B88: 45885 | C88: Flower Decoration - Ansh | D88: Ops | E88: No Bill | F88: 4000
A89: 45779 | B89: 45885 | C89: Prashad Container (200) | D89: Event | E89: 45885 | F89: 840
A90: 45810 | B90: 45885 | C90: 56 Bhog Thal | D90: Event | E90: 45885 | F90: 1850
A91: 45840 | B91: 45885 | C91: 10 Crates of Water - Pranay | D91: Event | E91: 45885 | F91: 1000
A92: 45871 | B92: 45885 | C92: 10 Crates of Water - akhilesh | D92: Event | E92: 45885 | F92: 1000
A93: 45902 | B93: 45885 | C93: Lights Decoration (6 Pieces) | D93: Event | E93: 45884 | F93: 4000
A94: 45932 | B94: 45885 | C94: Dhol Wala on janamashtami | D94: Event | E94: 45885 | F94: 1200
A95: 45963 | B95: 45885 | C95: Acrylic colors Big Box for Shivling | D95: Ops | E95: 45885 | F95: 260
A96: 45993 | B96: 45884 | C96: Mathura Peda Prashad for 15th Pooja | D96: Event | E96: 45884 | F96: 1500
A97: 2/13 | B97: 46250 | C97: Cells, Hit & Brush | D97: Ops | E97: 45885 | F97: 725
A98: 2/14 | B98: 45885 | C98: Carry bags (200) For prashad | D98: Event | E98: 45885 | F98: 300
A99: 2/15 | B99: 46253 | C99: Voucher Book(2) | D99: Ops | E99: 45888 | F99: 120
A100: 2/16 | B100: 45889 | C100: Dakshina to Shastri ji (Janamashtami - Thali + Daan Patra : 50%) | D100: Dakshina | E100: 45889 | F100: 7100
A101: 2/17 | B101: 45889 | C101: Naag Devta for Mandir | D101: Idols | E101: 45888 | F101: 5000
A102: 2/18 | B102: 45889 | C102: Chandan & Honey for Mandir | D102: Ops | E102: 45889 | F102: 840
A103: 2/19 | B103: 45892 | C103: Payment for Tent on Janamashtami | D103: Tent | E103: 45885 | F103: 16500
A104: 2/20 | B104: 45892 | C104: Rishi pathar wala payment | D104: Construction | E104: 45892 | F104: 10000
A105: 2/21 | B105: 45894 | C105: Love Catering ( Bhandara Payment - Janamashatami) | D105: Event | E105: 45885 | F105: 33000
A106: 2/22 | B106: 45894 | C106: Chokhat Payment Ti Mani Pal Goyal By Amit Katiyar | D106: Construction | E106: 45890 | F106: 12500
A107: 2/23 | B107: 45895 | C107: Payment for chemical 50 bags, 390 per bag | D107: Construction | E107: 45894 | F107: 19500
A108: 2/23-1 | B108: 45895 | C108: Advance payments for Rack | F108: 1000
A109: 2/24 | B109: 45896 | C109: Rishi pathar wala payment | D109: Construction | E109: 45896 | F109: 20000
A110: 2/25 | B110: 45896 | C110: 20 Cemet Bags - Payment to rishi | D110: Construction | E110: 45896 | F110: 17000
A111: 2/26 | B111: 45899 | C111: Payment to Harmeet Contractor | D111: Construction | E111: 45958 | F111: 30000
A112: 2/27 | B112: 45903 | C112: Payment to Rishi for Plaster Work & Tile Work Tilll2 Sep 2025 | D112: Construction | E112: 45903 | F112: 35000
A113: 2/28 | B113: 45903 | C113: Payment for Dholwala (700) & Jagannath (200) on Chati Event | D113: Ops | E113: 45903 | F113: 900
A114: 2/29 | B114: 45899 | C114: Racks Pending Payment (5650) + Carriage(400) | F114: 6050
A115: 2/30 | B115: 45899 | C115: God Idols: Shiv parivar & Hanuman Ji | D115: Idols | E115: 45899 | F115: 20000
A116: 2/31 | B116: 45906 | C116: Payment to Rishi for the work done on 4th Sep 2025 | D116: Construction | E116: 45906 | F116: 6000
A117: 2/32 | B117: 45907 | C117: Payment to rishi for Work done till 7th Sep 2025 | D117: Construction | E117: 45907 | F117: 12200
A118: 2/33 | B118: 45908 | C118: Payment for Red Stone & Carriage in cash | D118: Construction | E118: 45917 | F118: 6300
A119: 2/34 | B119: 45907 | C119: Red Stone Online Payment by mayank | D119: Construction | E119: 45907 | F119: 11340
A120: 2/35 | B120: 45908 | C120: Additional 3 Boxes + Carriage Tiles | D120: Construction | E120: 45904 | F120: 7975
A121: 2/36 | B121: 45908 | C121: Arolite for Mandir | D121: Construction | E121: 45893 | F121: 2000
A122: 2/37 | B122: 45909 | C122: Cement Bags for Outerwalls | D122: Construction | E122: 45909 | F122: 4000
A123: 2/38 | B123: 45909 | C123: Tile Adhesive Outewalls and Top (150 Bags Shiv Durga Mandir NCT - Donation & Expenses | D123: Construction | E123: 45909 | F123: 58500
A124: 2/39 | B124: 45911 | C124: Jeera Bajri 50-50 Ft HARMEET | D124: Construction | E124: 45958 | F124: 3600
A125: 2/40 | B125: 45911 | C125: Rishi pathar wala payment (8 Sep - 11 sep) | D125: Construction | E125: 45911 | F125: 18800
A126: 2/41 | B126: 45913 | C126: Payment to Harmeet Contractor (False Ceiling) | D126: Construction | E126: 45958 | F126: 15000
... A147: 2/62 | B147: 45947 | C147: Red Stone 500ft additional | D147: Construction | E147: 45947 | F147: 15500
A148: 2/63 | B148: 45952 | C148: Payment to Ansh Phool wala | D148: Ops | E148: No Bill | F148: 4800
A149: 2/64 | B149: 45952 | C149: Payment for Mandir work | D149: Ops | E149: 45952 | F149: 7120
A150: 2/65 | B150: 45952 | C150: Mandir Ghee + Honey | F150: 1394
A151: 2/66 | B151: 45952 | C151: Payment for Tent & Water Tanker ( Ankoot) | D151: Event | E151: 45952 | F151: 15500
...

Sheet Donation
A1: Sr.No | B1: Date | C1: Donor Name | D1: Phone Number | E1: Flat No. | F1: Mode | G1: Amount | H1: Reference No. | I1: Book/Receipt No | J1: Against Material | K1: Donation Amount With | L1: Amount Given To Treasurer | M1: Collection By | N1: Remarks
A2: 1 | B2: 45802 | C2: Rajesh Nanda Ji | D2: 9315118750 | E2: A1-PH3 | F2: Cash | G2: 11000 | I2: 45658 | K2: Akhilesh | L2: Yes | M2: Rajesh Nanda
A3: 2 | B3: 45802 | C3: Mayank Aggarwal | D3: 9910345533 | E3: B15 GF03 | F3: Cash | G3: 11000 | I3: 45689 | K3: Akhilesh | L3: Yes | M3: Mayank Aggarwal
A4: 3 | B4: 45802 | C4: Akhilesh Mahajan | D4: 9988556660 | E4: B1/404 | F4: Cash | G4: 11000 | I4: 45717 | K4: Akhilesh | L4: Yes | M4: Akhilesh Mahajan
A5: 4 | B5: 45802 | C5: Meenakshi Aggarwal | D5: 9592339372 | E5: C3-GF02 | F5: Cash | G5: 11000 | I5: 45748 | K5: Akhilesh | L5: Yes | M5: Mayank Aggarwal
A6: 5 | B6: 45802 | C6: Gaurav Mahajan | D6: 9888499800 | E6: B9/304 | F6: Cash | G6: 11000 | I6: 45778 | K6: Akhilesh | L6: Yes | M6: Gaurav Mahajan
A7: 6 | B7: 45802 | C7: Amit Vats | D7: 9815387986 | E7: C2/106 | F7: Cash | G7: 11000 | I7: 45809 | K7: Akhilesh | L7: Yes | M7: Amit Vats
A8: 7 | B8: 45802 | C8: Navin Garg | D8: 9814488999 | E8: B9/GF02 | F8: Cash | G8: 11000 | I8: 45839 | K8: Akhilesh | L8: Yes | M8: Akhilesh Mahajan
A9: 8 | B9: 45802 | C9: Padam Jain | D9: 9814815573 | E9: B14/ 403 | F9: Cash | G9: 11000 | I9: 45870 | K9: Akhilesh | L9: Yes | M9: Mayank Aggarwal
A10: 9 | B10: 45802 | C10: Anil Tandon | D10: 9872769299 | F10: Cash | G10: 11000 | I10: 45901 | K10: Akhilesh | L10: Yes | M10: Rajesh Nanda
A11: 10 | B11: 45802 | C11: Aman Sharma | E11: B13/504 | F11: Cash | G11: 11000 | I11: 45931 | K11: Akhilesh | L11: Yes | M11: Mayank Aggarwal
A12: 11 | B12: 45802 | C12: Pranay Srivastava | D12: 9216779477 | E12: B12/501 | F12: Cash | G12: 11000 | I12: 45962 | K12: Akhilesh | L12: Yes | M12: Pranay Srivastava
A13: 12 | B13: 45802 | C13: Saurabh Jain | E13: Noida | F13: Cash | G13: 2100 | I13: 45992 | K13: Akhilesh | L13: Yes | M13: Mayank Aggarwal
A14: 13 | B14: 45808 | C14: Mr.Gandhi | E14: A5 | F14: UPI | G14: 7000 | H14: 515104643031 | I14: 1/13 | J14: 1000 Bricks | K14: Amit Vats | L14: Yes | M14: Walk-In
A15: 14 | B15: 45808 | C15: Sh. Satish Kumar Nanda | E15: Ambala | F15: UPI | G15: 14000 | I15: 1/14 | J15: 2000 Bricks | K15: Nanda Ji | L15: Yes | M15: Rajesh Nanda | N15: Nanda Ji's Father
A16: 15 | B16: 45809 | C16: Kapil Sharma | E16: B12/204 | F16: UPI | G16: 11000 | I16: 1/15 | K16: Nanda Ji | L16: Yes | M16: Rajesh Nanda
A17: 16 | B17: 45809 | C17: Gupt Daan | F17: Cash | G17: 1100 | I17: 1/16 | K17: Akhilesh | L17: Yes | M17: Walk-In
A18: 17 | B18: 45810 | C18: Renu Sharma | E18: Silve City | F18: Cash | G18: 5000 | I18: 1/17 | K18: Akhilesh | L18: Yes | M18: Bajaj Aunty
A19: 18 | B19: 45810 | C19: Ankur Gupta | E19: Chennai | F19: Cash | G19: 5100 | I19: 1/18 | K19: Akhilesh | L19: Yes | M19: Akhilesh Mahajan | N19: Akhilesh's Jija Ji
A20: 19 | B20: 45810 | C20: Gupt Daan | F20: Cash | G20: 1100 | I20: 1/19 | K20: Pranay | L20: Yes | M20: Pranay Srivastava
A21: 20 | B21: 45810 | C21: Mr.S.K Sharma | E21: B12/402 | F21: Cash | G21: 5100 | I21: 1/20 | K21: Pranay | L21: Yes | M21: Pranay Srivastava
A22: 21 | B22: 45810 | C22: Neelu Soi | E22: C3/410 | F22: Cash | G22: 11000 | I22: 1/21 | K22: Akhilesh | L22: Yes | M22: Akhilesh Mahajan
A23: 22 | B23: 45810 | C23: Gupt Daan | F23: Cash | G23: 1000 | I23: 1/22 | K23: Akhilesh | L23: Yes | M23: Bajaj Aunty
A24: 23 | B24: 45810 | C24: Komal | E24: Silver City | F24: UPI | G24: 5200 | I24: 1/23 | K24: Nanda Ji | L24: Yes | M24: Walk-In
A25: 24 | B25: 45810 | C25: Attar Grewal(Rupi) | E25: D3 GF4 | F25: UPI | G25: 500 | I25: 1/24 | K25: Nanda Ji | L25: Yes | M25: Walk-In
A26: 25 | B26: 45810 | C26: Raju Chowdhury | F26: Cash | G26: 11001 | I26: 1/25 | K26: Nanda Ji | L26: Yes | M26: Rajesh Nanda
A27: 26 | B27: 45811 | C27: Gupt Daan | F27: Cash | G27: 5100 | I27: 1/26 | K27: Nanda Ji | L27: Yes | M27: Walk-In
A28: 27 | B28: 45812 | C28: Gurmeet Ji | E28: C4/402 | F28: Cash | G28: 5100 | I28: 1/27 | K28: Amit Vats | L28: Yes | M28: Amit Vats
A29: 28 | B29: 45812 | C29: Sh. Sudarshan Kumar | E29: B12/401 | F29: Cash | G29: 2100 | I29: 1/28 | K29: Pranay | L29: Yes | M29: Pranay Srivastava
A30: 29 | B30: 45812 | C30: Avinash Jaithely | E30: B12/604 | F30: Cash | G30: 501 | I30: 1/29 | K30: Pranay | L30: Yes | M30: Pranay Srivastava
A31: 30 | B31: 45812 | C31: Preeti Katiyar | E31: B-7/301 | F31: Cash | G31: 5100 | I31: 1/30 | K31: Akhilesh | L31: Yes | M31: Akhilesh Mahajan
A32: 31 | B32: 45812 | C32: Surinder Mahajan | E32: Amritsar | F32: Cash | G32: 5100 | I32: 1/31 | K32: Gaurav Mahajan | L32: Yes | M32: Gaurav Mahajan | N32: Gaurav Mahajan's Parents
A33: 32 | B33: 45812 | C33: Ashwani Mahajan | E33: Amritsar | F33: Cash | G33: 2100 | I33: 1/32 | K33: Gaurav Mahajan | L33: Yes | M33: Gaurav Mahajan | N33: Gaurav Mahajan's Brother in law
A34: 33 | B34: 45812 | C34: Dolly Marwaha | E34: Amritsar | F34: Cash | G34: 1100 | I34: 1/33 | K34: Gaurav Mahajan | L34: Yes | M34: Gaurav Mahajan | N34: Gaurav Mahajan's Sister in law
A35: 34 | B35: 45812 | C35: Abhishek | E35: C3-GF11 | F35: Cash | G35: 5100 | I35: 1/34 | K35: Team Meenaksi/Suchi | L35: Yes | M35: Team Meenakshi/Suchi
A36: 35 | B36: 45812 | C36: Khushi | E36: C4-503 | F36: Cash | G36: 2100 | I36: 1/35 | K36: Team Meenaksi/Suchi | L36: Yes | M36: Team Meenakshi/Suchi
A37: 36 | B37: 45812 | C37: Aarav Sethi | E37: C4/501 | F37: Cash | G37: 2100 | I37: 1/36 | K37: Team Meenaksi/Suchi | L37: Yes | M37: Team Meenakshi/Suchi
A38: 37 | B38: 45812 | C38: Trivik | E38: C4-601 | F38: Cash | G38: 2100 | I38: 1/37 | K38: Team Meenaksi/Suchi | L38: Yes | M38: Team Meenakshi/Suchi
A39: 38 | B39: 45812 | C39: Dr.Vishal | E39: C3-311 | F39: Cash | G39: 1100 | I39: 1/38 | K39: Team Meenaksi/Suchi | L39: Yes | M39: Team Meenakshi/Suchi
A40: 39 | B40: 45812 | C40: Sunaina | E40: C3-101 | F40: Cash | G40: 1100 | I40: 1/39 | K40: Team Meenaksi/Suchi | L40: Yes | M40: Team Meenakshi/Suchi
A41: 40 | B41: 45812 | C41: Vikas Sachdeva | E41: C4-GF3 | F41: Cash | G41: 1100 | I41: 1/40 | K41: Team Meenaksi/Suchi | L41: Yes | M41: Team Meenakshi/Suchi
A42: 41 | B42: 45812 | C42: Monica | E42: C4-502 | F42: Cash | G42: 500 | I42: 1/41 | K42: Team Meenaksi/Suchi | L42: Yes | M42: Team Meenakshi/Suchi
A43: 42 | B43: 45812 | C43: Akul Bajaj | E43: C3-309 | F43: Cash | G43: 500 | I43: 1/42 | K43: Team Meenaksi/Suchi | L43: Yes | M43: Team Meenakshi/Suchi
A44: 43 | B44: 45812 | C44: Rohit Sarpal | E44: C3-508 | F44: Cash | G44: 500 | I44: 1/43 | K44: Team Meenaksi/Suchi | L44: Yes | M44: Team Meenakshi/Suchi
A45: 44 | B45: 45812 | C45: Sumit Narang | E45: C3-207 | F45: Cash | G45: 1100 | I45: 1/44 | K45: Team Meenaksi/Suchi | L45: Yes | M45: Team Meenakshi/Suchi
A46: 45 | B46: 45812 | C46: Priyanka | E46: C3-312 | F46: Cash | G46: 500 | I46: 1/45 | K46: Team Meenaksi/Suchi | L46: Yes | M46: Team Meenakshi/Suchi
... A50: 49 | B50: 45812 | C50: Shanil | E50: C3-501 | F50: Cash | G50: 500 | I50: 1/49 | K50: Team Meenaksi/Suchi | L50: Yes | M50: Team Meenakshi/Suchi
A51: 50 | B51: 45812 | C51: Seema | E51: C4-401 | F51: Cash | G51: 200 | I51: 45659 | K51: Team Meenaksi/Suchi | L51: Yes | M51: Team Meenakshi/Suchi
A52: 51 | B52: 45812 | C52: Manoj Gupta | E52: C3-107 | F52: Cash | G52: 5100 | I52: 45690 | K52: Team Meenaksi/Suchi | L52: Yes | M52: Team Meenakshi/Suchi
A53: 52 | B53: 45812 | C53: Sagar | E53: C2-409 | F53: Cash | G53: 5100 | I53: 45718 | K53: Team Meenaksi/Suchi | L53: Yes | M53: Team Meenakshi/Suchi
A54: 53 | B54: 45812 | C54: Sushant | E54: C3-GF09 | F54: Cash | G54: 3100 | I54: 45749 | K54: Team Meenaksi/Suchi | L54: Yes | M54: Team Meenakshi/Suchi
A55: 54 | B55: 45812 | C55: K.K Chawla | E55: C3-105 | F55: Cash | G55: 2100 | I55: 45779 | K55: Team Meenaksi/Suchi | L55: Yes | M55: Team Meenakshi/Suchi
A56: 55 | B56: 45812 | C56: Rakesh Tikku | E56: C3-305 | F56: Cash | G56: 2100 | I56: 45810 | K56: Team Meenaksi/Suchi | L56: Yes | M56: Team Meenakshi/Suchi
A57: 56 | B57: 45812 | C57: Gupt Daan | F57: Cash | G57: 1100 | I57: 45840 | K57: Team Meenaksi/Suchi | L57: Yes | M57: Team Meenakshi/Suchi
A58: 57 | B58: 45812 | C58: Rakesh | E58: C3-511 | F58: Cash | G58: 1100 | I58: 45871 | K58: Team Meenaksi/Suchi | L58: Yes | M58: Team Meenakshi/Suchi
A59: 58 | B59: 45812 | C59: Rajni | E59: C4-101 | F59: Cash | G59: 1100 | I59: 45902 | K59: Team Meenaksi/Suchi | L59: Yes | M59: Team Meenakshi/Suchi
A60: 59 | B60: 45812 | C60: Sandhu | E60: C3-308 | F60: Cash | G60: 1100 | I60: 45932 | K60: Team Meenaksi/Suchi | L60: Yes | M60: Team Meenakshi/Suchi
A61: 60 | B61: 45812 | C61: Sudha | E61: C3-GF06 | F61: Cash | G61: 500 | I61: 45963 | K61: Team Meenaksi/Suchi | L61: Yes | M61: Team Meenakshi/Suchi
A62: 61 | B62: 45813 | C62: Sachin Kapoor | D62: 8630502641 | E62: 546-Silver City | F62: Cash | G62: 11000 | I62: 45993 | K62: Mayank | L62: Yes | M62: Bajaj Aunty
A63: 62 | B63: 45813 | C63: Sapna Kalya | D63: 9646886997 | E63: 548-Silver City | F63: Cash | G63: 11000 | I63: 2/13 | K63: Mayank | L63: Yes | M63: Bajaj Aunty
A64: 63 | B64: 45813 | C64: Hina Kalya/Rimpi Kaplish | D64: 9646886997 | E64: 548-Silver City | F64: Cash | G64: 5100 | I64: 2/14 | K64: Mayank | L64: Yes | M64: Bajaj Aunty
A65: 64 | B65: 45813 | C65: Pawan Khullar | D65: 8054332210 | E65: B8/302 | F65: Cash | G65: 31000 | I65: 2/15 | K65: Mayank | L65: Yes | M65: Mayank Aggarwal, Amit Vats
A66: 65 | B66: 45813 | C66: Deepak Ghambir | D66: 9992757755 | E66: C4/301 | F66: Cash | G66: 2100 | I66: 2/16 | K66: Mayank | L66: Yes | M66: Mayank Aggarwal
A67: 66 | B67: 45813 | C67: Anil Kumar Seth | D67: 9872812356 | E67: B8/203 | F67: Cash | G67: 2100 | I67: 2/17 | K67: Mayank | L67: Yes | M67: Mayank Aggarwal
A68: 67 | B68: 45813 | C68: Indu Dhall | D68: 9888439606 | E68: B15/302 | F68: Cash | G68: 11000 | I68: 2/18 | K68: Mayank | L68: Yes | M68: Mayank Aggarwal
A69: 68 | B69: 45814 | C69: Rohit Nagpal | D69: 7626891234 | E69: B7/202 | F69: Cash | G69: 5100 | I69: 2/19 | K69: Akhilesh | L69: Yes | M69: Akhilesh Mahajan
A70: 69 | B70: 45814 | C70: Sarabveer Singh | D70: 9872743875 | E70: B12/201 | F70: Cash | G70: 5100 | I70: 2/21 | K70: Pranay | L70: Yes | M70: Pranay Srivastava
A71: 70 | B71: 45823 | C71: Parveen Vij | E71: B15/D1 | F71: Cash | G71: 11000 | I71: 3/22 | K71: Nanda Ji | L71: Yes | M71: Rajesh Nanda
A72: 71 | B72: 45814 | C72: Lalit Jindal | E72: C3-402 | F72: Cash | G72: 2100 | I72: 2/22 | K72: Team Meenaksi/Suchi | L72: Yes | M72: Team Meenakshi/Suchi
A73: 72 | B73: 45814 | C73: Vivek Trivedi | E73: C3-201 | F73: Cash | G73: 5100 | I73: 2/23 | K73: Team Meenaksi/Suchi | L73: Yes | M73: Team Meenakshi/Suchi
A74: 73 | B74: 45814 | C74: Rajiv Sharma | E74: C3-GF07 | F74: Cash | G74: 5100 | I74: 2/24 | K74: Team Meenaksi/Suchi | L74: Yes | M74: Team Meenakshi/Suchi
A75: 74 | B75: 45814 | C75: Gupt Daan | F75: Cash | G75: 500 | I75: 2/25 | K75: Team Meenaksi/Suchi | L75: Yes | M75: Team Meenakshi/Suchi
A76: 75 | B76: 45814 | C76: Rashmi JI | D76: 9855024090 | E76: C2-304 | F76: Cash | G76: 5100 | I76: 2/26 | K76: Team Meenaksi/Suchi | L76: Yes | M76: Team Meenakshi/Suchi
A77: 76 | B77: 45814 | C77: Ekta | D77: 9872860937 | E77: C2-502 | F77: Cash | G77: 2100 | I77: 2/27 | K77: Team Meenaksi/Suchi | L77: Yes | M77: Team Meenakshi/Suchi
A78: 77 | B78: 45814 | C78: Rajesh Sharma | D78: 9357775551 | E78: C2-501 | F78: Cash | G78: 2100 | I78: 2/28 | K78: Team Meenaksi/Suchi | L78: Yes | M78: Team Meenakshi/Suchi
A79: 78 | B79: 45814 | C79: H.k Boutique | D79: 8146669337 | E79: C2-102 | F79: Cash | G79: 1500 | I79: 2/29 | K79: Team Meenaksi/Suchi | L79: Yes | M79: Team Meenakshi/Suchi
A80: 79 | B80: 45814 | C80: Jagriti | D80: 8278861394 | E80: C1-GF05 | F80: Cash | G80: 1100 | I80: 2/30 | K80: Team Meenaksi/Suchi | L80: Yes | M80: Team Meenakshi/Suchi
A81: 80 | B81: 45814 | C81: Baby Ji | D81: 9888521638 | E81: C1-604 | F81: Cash | G81: 1100 | I81: 2/31 | K81: Team Meenaksi/Suchi | L81: Yes | M81: Team Meenakshi/Suchi
A82: 81 | B82: 45814 | C82: Neeru | D82: 9872585231 | E82: C2-403 | F82: Cash | G82: 500 | I82: 2/32 | K82: Team Meenaksi/Suchi | L82: Yes | M82: Team Meenakshi/Suchi
A83: 82 | B83: 45814 | C83: Gupt Daan | F83: Cash | G83: 500 | I83: 2/33 | K83: Team Meenaksi/Suchi | L83: Yes | M83: Team Meenakshi/Suchi
A84: 83 | B84: 45814 | C84: Charu | F84: Cash | G84: 500 | I84: 2/34 | K84: Team Meenaksi/Suchi | L84: Yes | M84: Team Meenakshi/Suchi
A85: 84 | B85: 45814 | C85: LR Jangra | D85: 9316030909 | E85: B14-103 | F85: UPI | G85: 11000 | I85: 2/40 | K85: Mayank | L85: Yes | M85: Mayank Aggarwal
A86: 85 | B86: 45814 | C86: Ruchika Kapoor | D86: 7973027875 | E86: B4-302 | F86: UPI | G86: 5100 | I86: 2/41 | K86: Mayank | L86: Yes | M86: Mayank Aggarwal
A87: 86 | B87: 45814 | C87: Kiran Kochar | D87: 8586917272 | E87: B14/304 | F87: Cash | G87: 11000 | I87: 2/35 | K87: Mayank | L87: Yes | M87: Mayank Aggarwal
A88: 87 | B88: 45814 | C88: Soni Dhiman | D88: 9815118096 | E88: 1203, Silver City | F88: Cash | G88: 1000 | I88: 2/36 | K88: Mayank | L88: Yes | M88: Bajaj Aunty
A89: 88 | B89: 45814 | C89: Nirmal Bansal | D89: 989620911/8168246732 | E89: B4/202 | F89: Cash | G89: 31000 | I89: 2/20 | K89: Mayank | L89: Yes | M89: Mayank Aggarwal
A90: 89 | B90: 45814 | C90: Param | D90: 9876644158 | E90: C3-203 | F90: Cash | G90: 5100 | I90: 2/37 | K90: Team Meenaksi/Suchi | L90: Yes | M90: Team Meenakshi/Suchi
A91: 90 | B91: 45814 | C91: Rajesh Khonsla | D91: 9872807459 | E91: c2/502 | F91: UPI | G91: 3850 | I91: 2/38 | K91: Mayank | L91: Yes | M91: Walk-In | N91: 11 Bags Cement
A92: 91 | B92: 45816 | C92: Neelam Dhupar | D92: 9876590922 | E92: C3/411 | F92: Cash | G92: 1100 | I92: 2/39 | K92: Mayank | L92: Yes | M92: Bajaj Aunty
A93: 92 | B93: 45816 | C93: Mrs Karkara | D93: 9463046787 | E93: B12/103 | F93: Cash | G93: 3100 | I93: 2/42 | K93: Pranay | L93: Yes | M93: Pranay Srivastava
A94: 93 | B94: 45816 | C94: Bantu Rishi | D94: 8699010712 | E94: C3/08 | F94: Cash | G94: 5100 | I94: 2/43 | K94: Team Meenaksi/Suchi | L94: Yes | M94: Team Meenakshi/Suchi
A95: 94 | B95: 45816 | C95: Rinku Singh | D95: 8872324314 | E95: C2/108 | F95: Cash | G95: 2100 | I95: 2/44 | K95: Team Meenaksi/Suchi | L95: Yes | M95: Team Meenakshi/Suchi
A96: 95 | B96: 45816 | C96: Amita | F96: Cash | G96: 500 | I96: 2/45 | K96: Team Meenaksi/Suchi | L96: Yes | M96: Team Meenakshi/Suchi
A97: 96 | B97: 45816 | C97: Yoshita | F97: Cash | G97: 500 | I97: 2/46 | K97: Team Meenaksi/Suchi | L97: Yes | M97: Team Meenakshi/Suchi
A98: 97 | B98: 45816 | C98: Abhineet Sapra | E98: A5/101 | F98: Cash | G98: 11000 | I98: 2/47 | K98: Pranay | L98: Yes | M98: Pranay Srivastava
A99: 98 | B99: 45817 | C99: Mrs.Bhawna Gulati | E99: B9/403 | F99: Cash | G99: 2100 | I99: 4/21 | K99: Team Rajni/Sakhi | L99: Yes | M99: Team Rajni/Sakshi
A100: 99 | B100: 45817 | C100: Mrs.Shikha | E100: B9/303 | F100: Cash | G100: 1100 | I100: 4/22 | K100: Team Rajni/Sakhi | L100: Yes | M100: Team Rajni/Sakshi
A101: 100 | B101: 45817 | C101: Mehta Kiran | E101: B9/301 | F101: Cash | G101: 1600 | I101: 4/23 | K101: Team Rajni/Sakhi | L101: Yes | M101: Team Rajni/Sakshi
A102: 101 | B102: 45817 | C102: Vipin Puri | E102: B9/102 | F102: Cash | G102: 3100 | I102: 4/24 | K102: Team Rajni/Sakhi | L102: Yes | M102: Team Rajni/Sakshi
A103: 102 | B103: 45817 | C103: Anita Malik | E103: B9/603 | F103: Cash | G103: 2100 | I103: 4/25 | K103: Team Rajni/Sakhi | L103: Yes | M103: Team Rajni/Sakshi
...

Sheet Monthly Sheet
F1: Feburary 2026 | K1: 46082 | P1: 46113 | U1: 46143 | Z1: 46174 | AE1: 46204
A2: Sr.No | B2: Donar Name | C2: Collection By | D2: Phone | E2: Address | F2: Amount | G2: Status | H2: Payment Date | I2: Recipt No | J2: Mode | K2: Amount | L2: Status | M2: Payment Date | N2: Recipt No | O2: Mode | P2: Amount | Q2: Status | R2: Payment Date | S2: Recipt No | T2: Mode | U2: Amount | V2: Status | W2: Payment Date | X2: Recipt No | Y2: Mode | Z2: Amount | AA2: Status | AB2: Payment Date | AC2: Recipt No | AD2: Mode | AE2: Amount | AF2: Status | AG2: Payment Date | AH2: Receipt No | AI2: Mode
F3: =SUM(F4:F200) -> 12500 | K3: =sum(K4:K46) -> 8500 | P3: =sum(P4:P49) -> 8500 | U3: =sum(U4:U55) -> 3000 | Z3: =sum(Z4:Z1000) -> 4500 | AE3: =sum(AE4:AE1000) -> 2000
A4: 1 | B4: Akhilesh Mahajan | C4: Committee | D4: 9988556660 | E4: B1/404 | F4: 500 | G4: Paid | H4: 46071 | I4: SDM/1001 | J4: Cash | K4: 500 | L4: Paid | M4: 46089 | N4: SDM/1026
A5: 2 | B5: Mayank Aggarwal | C5: Committee | D5: 9910345533 | E5: B15/GF03 | F5: 500 | G5: Paid | H5: 46071 | I5: SDM/1002 | J5: Cash
A6: 3 | B6: Aanchal | C6: Team Rajni/Sakshi | D6: 9872790372 | E6: B15/301 | F6: 500 | G6: Paid | H6: 46072 | I6: SDM/1003 | J6: Cash | K6: 500 | L6: Paid | M6: 46096 | N6: SDM/1033 | P6: 500 | Q6: Paid | R6: 46132 | S6: SDM/1044 | T6: Cash
A7: 4 | B7: Neeti Sharma | C7: Team Rajni/Sakshi | D7: 9780333388 | E7: B12/204 | F7: 500 | G7: Paid | H7: 46072 | I7: SDM/1004 | J7: Cash | K7: 500 | L7: Paid | M7: 46096 | N7: SDM/1031 | O7: Cash | P7: 500 | Q7: Paid | R7: 46132 | S7: SDM/1042 | T7: Cash
A8: 5 | B8: Ruchi Gupta | C8: Team Rajni/Sakshi | D8: 9914903824 | E8: B14/101 | F8: 500 | G8: Paid | H8: 46072 | I8: SDM/1005 | J8: Cash | K8: 500 | L8: Paid | M8: 46096 | N8: SDM/1032 | O8: Cash | P8: 500 | Q8: Paid | R8: 46132 | S8: SDM/1043 | T8: Cash
A9: 6 | B9: Vipin Puri | C9: Team Rajni/Sakshi | D9: 9779397624 | E9: B9/102 | F9: 500 | G9: Paid | H9: 46072 | I9: SDM/1006 | J9: Cash | K9: 500 | L9: Paid | M9: 46096 | N9: SDM/1039 | O9: Cash | P9: 500 | Q9: Paid | R9: 46132 | S9: SDM/1051 | T9: Cash
A10: 7 | B10: Rajesh Nanda | C10: Committee | E10: A1/PH03 | F10: 500 | G10: Paid | H10: 46072 | I10: SDM/1007 | J10: Cash
A11: 8 | B11: Amit Vats | C11: Committee | E11: C2/106 | F11: 500 | G11: Paid | H11: 46072 | I11: SDM/1008 | J11: Cash
A12: 9 | B12: Navin Garg | C12: Committee | E12: B9/GF02 | F12: 500 | G12: Paid | H12: 46072 | I12: SDM/1009 | J12: Cash | K12: 500 | L12: Paid | M12: 46096 | N12: SDM/1041 | O12: Cash | P12: 500 | Q12: Paid | R12: 46132 | S12: SDM/1053 | T12: Cash
A13: 10 | B13: Gaurav Mahajan | C13: Committee | E13: B9/604 | F13: 500 | G13: Paid | H13: 46072 | I13: SDM/1010 | J13: Cash
A14: 11 | B14: Pranay Srivastava | C14: Committee | E14: B12/501 | F14: 500 | G14: Paid | H14: 46072 | I14: SDM/1011 | J14: Cash
A15: 12 | B15: Amit Katiyar | C15: Committee | E15: B7/301 | F15: 500 | G15: Paid | H15: 46072 | I15: SDM/1012 | J15: Cash | K15: 500 | L15: Paid | M15: 46089 | N15: SDM/1028 | O15: Cash
A16: 13 | B16: Khullar Aunty | C16: Team Rajni/Sakshi | D16: 7837179012 | E16: B8/302 | F16: 500 | G16: Paid | H16: 46074 | I16: SDM/1013 | J16: Cash | K16: 500 | L16: Paid | M16: 46096 | N16: SDM/1034 | O16: Cash | P16: 500 | Q16: Paid | R16: 46132 | S16: SDM/1046 | T16: Cash | U16: 500 | V16: Paid | W16: 46207 | X16: SDM/1077 | Y16: Cash
A17: 14 | B17: Aditya Nautiyal | C17: Gaurav Mahajan | D17: 9817685000 | E17: D2/603 | F17: 500 | G17: Paid | H17: 46075 | I17: SDM/1014 | J17: Cash
A18: 15 | B18: Hareet Goyal | C18: Gaurav Mahajan | E18: B3/GF01 | F18: 500 | G18: Paid | H18: 46075 | I18: SDM/1015 | J18: Cash
A19: 16 | B19: Dinesh Saklani | C19: Gaurav Mahajan | F19: 500 | G19: Paid | H19: 46075 | I19: SDM/1016 | J19: Cash
A20: 17 | B20: Ish Madaan | C20: Gaurav Mahajan | D20: 9916833888 | E20: B4/402 | F20: 500 | G20: Paid | H20: 46075 | I20: SDM/1017 | J20: Cash
A21: 18 | B21: Sharma Ji | C21: Gaurav Mahajan | D21: 8558986533 | E21: B13/GF03 | F21: 500 | G21: Paid | H21: 46075 | I21: SDM/1018 | J21: Cash
A22: 19 | B22: Manju | C22: Team Rajni/Sakshi | D22: 9988892225 | E22: B8/103 | F22: 500 | G22: Paid | H22: 46076 | I22: SDM/1019 | J22: Cash
A23: 20 | B23: Shikha Mittal | C23: Team Rajni/Sakshi | D23: 8427924051 | E23: B9/303 | F23: 500 | G23: Paid | H23: 46076 | I23: SDM/1020 | J23: Cash | K23: 500 | L23: Paid | M23: 46096 | N23: SDM/1036 | P23: 500 | Q23: Paid | R23: 46132 | S23: SDM/1048 | T23: Cash
A24: 21 | B24: Rohit Nagpal | C24: Akhilesh Mahajan | D24: 9876777108 | E24: B7/202 | F24: 500 | G24: Paid | H24: 46076 | I24: SDM/1021 | J24: Cash
A25: 22 | B25: Ravi Kant | C25: Akhilesh Mahajan | D25: 8837859411 | E25: C2/212 | F25: 500 | G25: Paid | H25: 46078 | I25: SDM/1022 | J25: Cash
A26: 23 | B26: Dina Nath Rajolia | C26: Akhilesh Mahajan | E26: patiala | F26: 500 | G26: Paid | H26: 46079 | I26: SDM/1023 | J26: Cash
A27: 24 | B27: Rana Ji | C27: Gaurav Mahajan | D27: 9991703366 | F27: 500 | G27: Paid | H27: 46079 | I27: SDM/1024 | J27: Cash | K27: 500 | L27: Paid | M27: 46083 | N27: SDM/1026 | O27: Cash | Z27: 500 | AA27: Paid | AB27: 46175 | AC27: SDM/1060 | AD27: Cash | AE27: 500 | AF27: Paid | AG27: 46231 | AI27: Cash
A28: 25 | B28: Lalit Ji | C28: Akhilesh Mahajan | E28: C3/404 | K28: 500 | L28: Paid | M28: 46083 | N28: SDM/1025 | O28: Cash
A29: 26 | B29: Kamal Hasija | C29: Akhilesh Mahajan | K29: 500 | L29: Paid | M29: 46096 | N29: SDM/1030 | O29: Cash | P29: 500 | Q29: Paid | R29: 46175 | S29: SDM/1061 | T29: Cash | U29: 500 | V29: Paid | W29: 46175 | X29: SDM/1062 | Y29: Cash | Z29: 500 | AA29: Paid | AB29: 46175 | AC29: SDM/1063 | AD29: Cash
A30: 27 | B30: Ruchi Aggarwal | C30: Team Rajni/Sakshi | E30: Silver City | K30: 500 | L30: Paid | M30: 46096 | N30: SDM/1035 | O30: Cash | P30: 500 | Q30: Paid | R30: 46132 | S30: SDM/1047 | T30: Cash
A31: 28 | B31: Nirmal Bansal | C31: Team Rajni/Sakshi | E31: B4/202 | K31: 500 | L31: Paid | M31: 46096 | N31: SDM/1037 | O31: Cash | P31: 500 | Q31: Paid | R31: 46132 | S31: SDM/1049 | T31: Cash | Z31: 500 | AA31: Paid | AB31: 46183 | AC31: SDM/1065 | AD31: Cash | AE31: 500 | AF31: Paid | AG31: 46207 | AH31: SDM/1076 | AI31: Cash
A32: 29 | B32: Tripta Garg | C32: Team Rajni/Sakshi | E32: B4/GF02 | K32: 500 | L32: Paid | M32: 46096 | N32: SDM/1038 | O32: Cash | P32: 500 | Q32: Paid | R32: 46132 | S32: SDM/1050 | T32: Cash
A33: 30 | B33: Gaurav Kumar | C33: Team Rajni/Sakshi | E33: B11/GF04 | K33: 500 | L33: Paid | M33: 46096 | N33: SDM/1040 | O33: Cash | P33: 500 | Q33: Paid | R33: 46132 | S33: SDM/1052 | T33: Cash
A34: 31 | B34: Rakesh Karkara | C34: Team Rajni/Sakshi | E34: B12/103 | P34: 500 | Q34: Paid | R34: 46132 | S34: SDM/1045 | T34: Cash
A35: 32 | B35: Prashant Chugh | C35: Akhilesh Mahajan | E35: B11/303
A36: 33 | B36: Padam Jain | C36: Rajesh Nanda | E36: B14 | F36: 500 | G36: Paid | H36: 46175 | I36: SDM/1054 | J36: Cash | K36: 500 | L36: Paid | M36: 46175 | N36: SDM/1055 | O36: Cash | P36: 500 | Q36: Paid | R36: 46175 | S36: SDM/1056 | T36: Cash | U36: 500 | V36: Paid | W36: 46175 | X36: SDM/1057 | Y36: Cash | Z36: 500 | AA36: Paid | AB36: 46175 | AC36: SDM/1058 | AD36: Cash | AE36: 500 | AF36: Paid | AG36: 46175 | AH36: SDM/1059 | AI36: Cash
A37: 34 | B37: Rani Taneja | C37: Team Rajni/Sakshi | Z37: 500 | AA37: Paid | AB37: 46183 | AC37: SDM/1064 | AD37: Cash
A38: 35 | B38: Himani Sharma | C38: Team Meenakshi/Suchi | P38: 500 | Q38: Paid | R38: 46183 | S38: SDM/1066 | T38: Cash | U38: 500 | V38: Paid | W38: 46183 | X38: SDM/1067 | Y38: Cash | Z38: 500 | AA38: Paid | AB38: 46183 | AC38: SDM/1068 | AD38: Cash
A39: 36 | B39: Sagar Kataria | C39: Team Meenakshi/Suchi | P39: 500 | Q39: Paid | R39: 46183 | S39: SDM/1069 | T39: Cash | U39: 500 | V39: Paid | W39: 46183 | X39: SDM/1070 | Y39: Cash | Z39: 500 | AA39: Paid | AB39: 46183 | AC39: SDM/1071 | AD39: Cash
A40: 37 | B40: PArul Munjal | C40: Team Meenakshi/Suchi | P40: 500 | Q40: Paid | R40: 46183 | S40: SDM/1072 | T40: Cash | U40: 500 | V40: Paid | W40: 46183 | X40: SDM/1073 | Y40: Cash | Z40: 500 | AA40: Paid | AB40: 46183 | AC40: SDM/1074 | AD40: Cash
A41: 38 | B41: Bunty Bhabhi | C41: Team Meenakshi/Suchi | Z41: 500 | AA41: Paid | AB41: 46183 | AC41: SDM/1075 | AD41: Cash
A42: 39 | B42: Asha Bajaj Aunty | AE42: 500 | AF42: Paid | AG42: 46207 | AH42: SDM/1078 | AI42: Cash
A43: 40
A44: 41
A45: 42
A46: 43
A47: 44
A48: 45
A49: 46
A50: 47
A51: 48
A52: 49
A53: 50
A54: 51
... A256: 253

Sheet Murti Collection
A1: Date | B1: Donor Name | C1: Phone Number | D1: Flat No. | E1: Mode | F1: Amount | G1: Reference No. | H1: Book/Receipt No | I1: Against Material | J1: Donation Amount With | K1: Amount Given To Treasurer | L1: Collection By | M1: Remarks | O1: Head | P1: Amount | Q1: Date
F2: =SUM(F3:F21) -> 620801 | P2: =SUM(P3:P13) -> 601300 | T2: Murti's Cost | U2: 660101
A3: 45919 | B3: Mr.Ravi Prabhakar | C3: 9872669185 | D3: B11/603 | E3: Cash | F3: 101000 | H3: SDM/7 | J3: Akhilesh | K3: Yes | L3: Mayank Aggarwal | O3: Advance | P3: 125000 | Q3: 45922 | T3: Collection | U3: =F2 -> 620801
A4: 45920 | B4: Mr Padam Jain | C4: 9814815573 | D4: B14 | E4: Cash | F4: 51000 | H4: SDM/8 | J4: Akhilesh | K4: Yes | L4: Mayank Aggarwal | O4: 1st Installment | P4: 196000 | Q4: 45939 | T4: Amount Paid | U4: =P2 -> 601300
A5: 45920 | B5: Gupt Daan | E5: Cash | F5: 61000 | H5: SDM/10 | J5: Akhilesh | K5: Yes | L5: Mayank Aggarwal | O5: 2nd Installment | P5: 98000 | Q5: 45971 | T5: In Hand | U5: =U3-U4 -> 19501
A6: 45921 | B6: Anil Tandon ji | C6: 9872769299 | E6: Cash | F6: 11000 | H6: SDM/517 | J6: Akhilesh | K6: Yes | L6: Mayank Aggarwal | O6: Final Payment | P6: 182300 | Q6: 45978 | T6: Short Money | U6: =U2-U3 -> 39300
A7: 45921 | B7: Soi Family | D7: C Block | E7: Cash | F7: 5100 | H7: SDM/518 | J7: Akhilesh | K7: Yes | L7: Mayank Aggarwal
A8: 45921 | B8: Lucky (Krishan Bhayana) | D8: B1/404 | E8: Cash | F8: 501 | H8: SDM/519 | J8: Akhilesh | K8: Yes | L8: Mayank Aggarwal
A9: 45922 | B9: Suresh Goyal | E9: Cash | F9: 5100 | H9: SDM/520 | J9: Akhilesh | K9: Yes | L9: Mayank Aggarwal
A10: 45922 | B10: Aayansh Mahajan | C10: 9988556660 | D10: B1/404 | E10: Cash | F10: 3100 | H10: SDM/521 | J10: Akhilesh | K10: Yes | L10: Mayank Aggarwal
A11: 45920 | B11: Mr. Abhiney Sharma | D11: B15/GF03 | E11: Cash | F11: 121000 | H11: SDM/11 | J11: Akhilesh | K11: Yes | L11: Mayank Aggarwal
A12: 45950 | B12: Mr. Nanda | E12: Cash | F12: 200000 | H12: SDM/538 | J12: Akhilesh | K12: Yes | L12: Rajesh Nanda
A13: 45970 | B13: Gupt Daan | E13: Cash | F13: 21000 | H13: SDM/541 | J13: Akhilesh | K13: Yes | L13: Akhilesh Mahajan
B14: Amit Vats | E14: Cash | F14: 21000 | H14: SDM/546 | J14: Akhilesh | K14: Yes | L14: Akhilesh Mahajan
B15: Meenakshi Bhabhi | D15: C3 Gf03 | E15: Cash | F15: 20000 | H15: SDM/19 | J15: Akhilesh | K15: Yes | L15: Akhilesh Mahajan

Sheet janamashtami Expenses
A1: Sr.No | B1: Expense | C1: Amount | D1: Expense By
A3: 1 | B3: Ballon Decoration | C3: 2200 | D3: Mayank
A4: 2 | B4: Flower Decoration | C4: 4000 | D4: Comitee
A5: 3 | B5: Fruits | C5: 1350 | D5: Mayank
A6: 4 | B6: Disposals (Dhona, Plates, etc) | C6: 1050 | D6: Mayank
A7: 5 | B7: Prasad Boxes | C7: 840 | D7: Comitee
A8: 6 | B8: Mandir MCB | C8: 220 | D8: Mayank
A9: 7 | B9: 56 Bhog | C9: 1850 | D9: Akhilesh
A10: 8 | B10: 10 Water Crates | C10: 1000 | D10: Pranay
A11: 9 | B11: 10 Water Crates | C11: 1000 | D11: Akhilesh
A12: 10 | B12: Dhol | C12: 1200 | D12: Comitee
A13: 12 | B13: Lights(6) | C13: 4000 | D13: Comitee
A14: 13 | B14: Colors | C14: 260 | D14: Akhilesh
... A19: 18 | B19: Mathura Peda | C19: 1500 | D19: Amit Vats
C21: =SUM(C3:C19) -> 21745
